odoo10_addon_purchase_landed_cost-10.0.2.0.0.99.dev15-py3.8-nspkg.pth
odoo/addons/purchase_landed_cost/README.rst
odoo/addons/purchase_landed_cost/__init__.py
odoo/addons/purchase_landed_cost/__manifest__.py
odoo/addons/purchase_landed_cost/data/purchase_cost_distribution_sequence.xml
odoo/addons/purchase_landed_cost/i18n/es.po
odoo/addons/purchase_landed_cost/i18n/fr.po
odoo/addons/purchase_landed_cost/i18n/it.po
odoo/addons/purchase_landed_cost/i18n/pt_BR.po
odoo/addons/purchase_landed_cost/i18n/purchase_landed_cost.pot
odoo/addons/purchase_landed_cost/i18n/ro.po
odoo/addons/purchase_landed_cost/i18n/sl.po
odoo/addons/purchase_landed_cost/models/__init__.py
odoo/addons/purchase_landed_cost/models/account_invoice.py
odoo/addons/purchase_landed_cost/models/format_lang_wrapper.py
odoo/addons/purchase_landed_cost/models/purchase_cost_distribution.py
odoo/addons/purchase_landed_cost/models/purchase_expense_type.py
odoo/addons/purchase_landed_cost/models/purchase_order.py
odoo/addons/purchase_landed_cost/models/stock_picking.py
odoo/addons/purchase_landed_cost/security/ir.model.access.csv
odoo/addons/purchase_landed_cost/security/purchase_landed_cost_security.xml
odoo/addons/purchase_landed_cost/static/description/icon.png
odoo/addons/purchase_landed_cost/static/description/images/expenses_types.png
odoo/addons/purchase_landed_cost/static/description/images/purchase_order_expense_line.png
odoo/addons/purchase_landed_cost/static/description/images/purchase_order_expense_main.png
odoo/addons/purchase_landed_cost/tests/__init__.py
odoo/addons/purchase_landed_cost/tests/test_purchase_landed_cost.py
odoo/addons/purchase_landed_cost/views/account_invoice_view.xml
odoo/addons/purchase_landed_cost/views/purchase_cost_distribution_line_expense_view.xml
odoo/addons/purchase_landed_cost/views/purchase_cost_distribution_view.xml
odoo/addons/purchase_landed_cost/views/purchase_expense_type_view.xml
odoo/addons/purchase_landed_cost/views/purchase_order_view.xml
odoo10_addon_purchase_landed_cost-10.0.2.0.0.99.dev15.dist-info/METADATA
odoo10_addon_purchase_landed_cost-10.0.2.0.0.99.dev15.dist-info/WHEEL
odoo10_addon_purchase_landed_cost-10.0.2.0.0.99.dev15.dist-info/namespace_packages.txt
odoo10_addon_purchase_landed_cost-10.0.2.0.0.99.dev15.dist-info/top_level.txt
odoo10_addon_purchase_landed_cost-10.0.2.0.0.99.dev15.dist-info/RECORD
