Metadata-Version: 2.1
Name: odoo10-addon-purchase-landed-cost
Version: 10.0.2.0.0.99.dev15
Summary: Purchase cost distribution
Home-page: https://github.com/OCA/purchase-workflow
Author: OdooMRP team,AvanzOSC,Tecnativa,Joaquín Gutierrez,Odoo Community Association (OCA)
Author-email: support@odoo-community.org
License: AGPL-3
Platform: UNKNOWN
Classifier: Programming Language :: Python
Classifier: Framework :: Odoo
Classifier: Framework :: Odoo :: 10.0
Classifier: License :: OSI Approved :: GNU Affero General Public License v3
Requires-Python: ~=2.7
Requires-Dist: odoo <10.1dev,>=10.0
